snipfile/__init__.py
snipfile/_base.py
snipfile/_file.py
snipfile/_holes.py
snipfile/_join.py
snipfile/_slice.py
snipfile-0.2.2.dist-info/METADATA
snipfile-0.2.2.dist-info/WHEEL
snipfile-0.2.2.dist-info/licenses/LICENSE
snipfile-0.2.2.dist-info/RECORD
