Metadata-Version: 2.4
Name: snipfile
Version: 0.2.2
Summary: provides functions to cut and merge file-objects in python
Project-URL: Homepage, https://github.com/mreithub/py-snipfile
Project-URL: Bug Tracker, https://github.com/mreithub/py-snipfile/issues
License-File: LICENSE
Classifier: License :: OSI Approved :: MIT License
Classifier: Operating System :: OS Independent
Classifier: Programming Language :: Python :: 3
Requires-Python: >=3.8
